igwp/__init__.py
igwp/_nbdev.py
igwp/core.py
igwp/plotting.py
igwp/data/RCP3PD_EMISSIONS.csv
igwp/data/RCP45_EMISSIONS.csv
igwp/data/RCP6_EMISSIONS.csv
igwp/data/RCP85_EMISSIONS.csv
igwp-0.0.1.dist-info/LICENSE
igwp-0.0.1.dist-info/METADATA
igwp-0.0.1.dist-info/WHEEL
igwp-0.0.1.dist-info/entry_points.txt
igwp-0.0.1.dist-info/top_level.txt
igwp-0.0.1.dist-info/RECORD
