Metadata-Version: 2.1
Name: igwp
Version: 0.0.1
Summary: Improved Global Warming Potential
Home-page: https://github.com/hydrocomputing/igwp/tree/master/
Author: Mike Müller
Author-email: mmueller@hydrocomputing.com
License: MIT License
Keywords: climate change,short-lived climate pollutions,methane
Platform: UNKNOWN
Classifier: Development Status :: 3 - Alpha
Classifier: Intended Audience :: Developers
Classifier: License :: OSI Approved :: MIT License
Classifier: Natural Language :: English
Classifier: Programming Language :: Python :: 3.6
Classifier: Programming Language :: Python :: 3.7
Classifier: Programming Language :: Python :: 3.8
Classifier: Programming Language :: Python :: 3.9
Requires-Python: >=3.6
Requires-Dist: pandas
Requires-Dist: matplotlib
Requires-Dist: fair
